imgtrf/__init__.py
imgtrf/__main__.py
imgtrf/cli.py
imgtrf/core.py
imgtrf/exceptions.py
imgtrf/logger.py
imgtrf/meta.py
image_transfer-0.2.0.dist-info/LICENCE.txt
image_transfer-0.2.0.dist-info/METADATA
image_transfer-0.2.0.dist-info/WHEEL
image_transfer-0.2.0.dist-info/entry_points.txt
image_transfer-0.2.0.dist-info/top_level.txt
image_transfer-0.2.0.dist-info/RECORD
