Metadata-Version: 2.1
Name: image-transfer
Version: 0.2.0
Summary: Transfer images and videos from one directoy to another with new folder structure by date
Author: Magnus Sommarsjö
Project-URL: Homepage, https://github.com/magnussommarsjo/image_transfer
Project-URL: Bug Tracker, https://github.com/magnussommarsjo/image_transfer/issues
Classifier: Programming Language :: Python :: 3
Classifier: License :: OSI Approved :: MIT License
Classifier: Operating System :: OS Independent
Classifier: Environment :: Console
Classifier: Topic :: Multimedia :: Graphics :: Capture :: Digital Camera
Classifier: Development Status :: 3 - Alpha
Requires-Python: >=3.8
License-File: LICENCE.txt
Requires-Dist: typer
Requires-Dist: rich
Requires-Dist: Pillow
Requires-Dist: ffmpeg-python
Provides-Extra: dev
Requires-Dist: image-transfer[test] ; extra == 'dev'
Requires-Dist: black ; extra == 'dev'
Provides-Extra: test
Requires-Dist: piexif ; extra == 'test'
Requires-Dist: pytest (>=6.0) ; extra == 'test'
